jojoba_proto/__init__.py
jojoba_proto/auth_pb2.py
jojoba_proto/auth_pb2.pyi
jojoba_proto/auth_pb2_grpc.py
jojoba_proto/matcher_pb2.py
jojoba_proto/matcher_pb2.pyi
jojoba_proto/matcher_pb2_grpc.py
jojoba_proto/profile_pb2.py
jojoba_proto/profile_pb2.pyi
jojoba_proto/profile_pb2_grpc.py
jojoba_proto/py.typed
jojoba_proto-0.2.0.dist-info/WHEEL
jojoba_proto-0.2.0.dist-info/METADATA
jojoba_proto-0.2.0.dist-info/RECORD
