Metadata-Version: 2.1
Name: jojoba-proto
Version: 0.2.0
Summary: 
Author: Heorhii Torianyk
Author-email: deadstonepro@gmail.com
Requires-Python: >=3.8,<4.0
Classifier: Programming Language :: Python :: 3
Classifier: Programming Language :: Python :: 3.8
Classifier: Programming Language :: Python :: 3.9
Classifier: Programming Language :: Python :: 3.10
Classifier: Programming Language :: Python :: 3.11
Requires-Dist: grpcio-tools (>=1.51.1,<2.0.0)
